fhdoc/__init__.py
fhdoc/__main__.py
fhdoc/ast_parser/__init__.py
fhdoc/ast_parser/analyzers/__init__.py
fhdoc/ast_parser/analyzers/base_analyzer.py
fhdoc/ast_parser/analyzers/class_analyzer.py
fhdoc/ast_parser/analyzers/expression_analyzer.py
fhdoc/ast_parser/analyzers/function_analyzer.py
fhdoc/ast_parser/analyzers/module_analyzer.py
fhdoc/ast_parser/enums.py
fhdoc/ast_parser/module_record_list.py
fhdoc/ast_parser/node_records/__init__.py
fhdoc/ast_parser/node_records/argument_record.py
fhdoc/ast_parser/node_records/attribute_record.py
fhdoc/ast_parser/node_records/class_record.py
fhdoc/ast_parser/node_records/expression_record.py
fhdoc/ast_parser/node_records/function_record.py
fhdoc/ast_parser/node_records/import_record.py
fhdoc/ast_parser/node_records/module_record.py
fhdoc/ast_parser/node_records/node_record.py
fhdoc/ast_parser/node_records/text_record.py
fhdoc/ast_parser/type_defs.py
fhdoc/cli_parser.py
fhdoc/generator.py
fhdoc/loader.py
fhdoc/main.py
fhdoc/md_document.py
fhdoc/processors/__init__.py
fhdoc/processors/base.py
fhdoc/processors/pep257.py
fhdoc/processors/rst.py
fhdoc/processors/section_map.py
fhdoc/processors/smart.py
fhdoc/settings.py
fhdoc/utils/__init__.py
fhdoc/utils/docstring_formatter.py
fhdoc/utils/import_string.py
fhdoc/utils/indent_trimmer.py
fhdoc/utils/logger.py
fhdoc/utils/path_finder.py
fhdoc-2021.0.2.dist-info/entry_points.txt
fhdoc-2021.0.2.dist-info/LICENSE.md
fhdoc-2021.0.2.dist-info/WHEEL
fhdoc-2021.0.2.dist-info/METADATA
fhdoc-2021.0.2.dist-info/RECORD
